fprules/__init__.py
fprules/_version.py
fprules/main.py
fprules/py.typed
fprules-0.3.0.dist-info/LICENSE
fprules-0.3.0.dist-info/METADATA
fprules-0.3.0.dist-info/WHEEL
fprules-0.3.0.dist-info/top_level.txt
fprules-0.3.0.dist-info/RECORD
