Metadata-Version: 2.1
Name: fprules
Version: 0.3.0
Summary: `make`-like file pattern rules for build tools such as `doit`.
Home-page: https://github.com/smarie/python-fprules
Maintainer: Sylvain MARIE
Maintainer-email: sylvain.marie@se.com
License: BSD 3-Clause
Download-URL: https://github.com/smarie/python-fprules/tarball/0.3.0
Keywords: file pattern rule rules GNU make build tool task
Platform: UNKNOWN
Classifier: Development Status :: 5 - Production/Stable
Classifier: Intended Audience :: Developers
Classifier: Topic :: Software Development :: Libraries :: Python Modules
Classifier: License :: OSI Approved :: BSD License
Classifier: Programming Language :: Python :: 2.7
Classifier: Programming Language :: Python :: 3.5
Classifier: Programming Language :: Python :: 3.6
Classifier: Programming Language :: Python :: 3.7
Requires-Dist: pathlib2 ; python_version < "3.2"
Requires-Dist: makefun ; python_version >= "3.6"
